malwaredb/__init__.py
malwaredb/malwaredb.abi3.so
malwaredb-0.3.0.dist-info/METADATA
malwaredb-0.3.0.dist-info/WHEEL
malwaredb.libs/libgcc_s-f685abf1.so.1
malwaredb-0.3.0.dist-info/RECORD
