Metadata-Version: 2.4
Name: malwaredb
Version: 0.3.0
Classifier: Development Status :: 4 - Beta
Classifier: Intended Audience :: Information Technology
Classifier: Intended Audience :: Science/Research
Classifier: License :: OSI Approved :: Apache Software License
Classifier: Programming Language :: Rust
Classifier: Programming Language :: Python :: Implementation :: CPython
Classifier: Programming Language :: Python :: Implementation :: PyPy
Classifier: Topic :: Communications :: File Sharing
Summary: Python client for MalwareDB
Keywords: cybersecurity,database,forensics,malware,research
Home-Page: https://malwaredb.net/
Author-email: Richard Zak <richard.j.zak@gmail.com>
License-Expression: Apache-2.0
Requires-Python: >=3.7
Project-URL: Changelog, https://github.com/malwaredb/malwaredb-rs/blob/main/log.md
Project-URL: Homepage, https://malwaredb.net
Project-URL: Issues, https://github.com/malwaredb/malwaredb-rs/issues
Project-URL: Repository, https://github.com/malwaredb/malwaredb-rs
